README.md
setup.py
fast_rub/Client.py
fast_rub/__init__.py
fast_rub/filters.py
fast_rub/test.py
fast_rub/version.py
fast_rub.egg-info/PKG-INFO
fast_rub.egg-info/SOURCES.txt
fast_rub.egg-info/dependency_links.txt
fast_rub.egg-info/requires.txt
fast_rub.egg-info/top_level.txt