Metadata-Version: 2.4
Name: fast_rub
Version: 1.0
Summary: the library for rubika bots.
Home-page: https://github.com/OandONE/fast_rub
Author: seyyed mohamad hosein moosavi raja(01)
Author-email: mohamadhosein159159@gmail.com
License: MIT
Requires-Python: >=3.8
Requires-Dist: httpx==0.28.1
Requires-Dist: colorama==0.4.6
Dynamic: author
Dynamic: author-email
Dynamic: description
Dynamic: description-content-type
Dynamic: home-page
Dynamic: license
Dynamic: requires-dist
Dynamic: requires-python
Dynamic: summary
